ncorpos_vi/__init__.py
ncorpos_vi/_version.py
ncorpos_vi/api.py
ncorpos_vi/_core/__init__.py
ncorpos_vi/_core/_core.cpython-313-x86_64-linux-gnu.so
ncorpos_vi/_core/libutilidades.so
ncorpos_vi/_core/libvalores_iniciais.so
ncorpos_vi/ext/ncorpos_valores_iniciais/python/exemplo.py
ncorpos_vi/ext/ncorpos_valores_iniciais/python/valores_iniciais/__init__.py
ncorpos_vi_py.libs/libblas-fe34f726.so.3.8.0
ncorpos_vi_py.libs/libgfortran-83c28eba.so.5.0.0
ncorpos_vi_py.libs/liblapack-31d7d384.so.3.8.0
ncorpos_vi_py.libs/libopenblas-r0-11edc3fa.3.15.so
ncorpos_vi_py.libs/libquadmath-2284e583.so.0.0.0
ncorpos_vi_py-1.0.2.dist-info/METADATA
ncorpos_vi_py-1.0.2.dist-info/WHEEL
ncorpos_vi_py-1.0.2.dist-info/RECORD
ncorpos_vi_py-1.0.2.dist-info/licenses/LICENSE
ncorpos_vi_py-1.0.2.dist-info/sboms/auditwheel.cdx.json
