Metadata-Version: 2.2
Name: ncorpos-vi-py
Version: 1.0.2
Summary: Geração de valores iniciais para problemas de N-corpos via fortran
Keywords: n-corpos
Author-Email: potalej <oapotalej@gmail.com>
Maintainer-Email: potalej <oapotalej@gmail.com>
License: Copyright (c) 2025 Octavio A. Potalej
Project-URL: Repository, https://github.com/potalej/ncorpos-vi-py
Requires-Dist: numpy
Requires-Dist: ncorpos-utilidades-py>=1.0.1
